activedirectorytoolsforpython.py
activedirectorytoolsforpython-0.2.0.dist-info/LICENSE.txt
activedirectorytoolsforpython-0.2.0.dist-info/METADATA
activedirectorytoolsforpython-0.2.0.dist-info/WHEEL
activedirectorytoolsforpython-0.2.0.dist-info/entry_points.txt
activedirectorytoolsforpython-0.2.0.dist-info/top_level.txt
activedirectorytoolsforpython-0.2.0.dist-info/RECORD
