Metadata-Version: 2.1
Name: activedirectorytoolsforpython
Version: 0.2.0
Summary: Set of tools for Active Directory using python.
Home-page: https://newgit.inuxnet.org/devel/activedirectorytoolsforpython
Author: Jess Williams
Author-email: Jess Williams <devel@inuxnet.org>
License: MIT License
Project-URL: Homepage, https://newgit.inuxnet.org/devel/activedirectorytoolsforpython
Project-URL: Documentation, https://newgit.inuxnet.org/devel/activedirectorytoolsforpython
Project-URL: Repository, https://newgit.inuxnet.org/devel/activedirectorytoolsforpython
Keywords: ad,activedirectory,ldap,get-aduser,powershell,get-adgroup,get-adorganizationalunit,get-adobject
Classifier: Intended Audience :: Developers
Classifier: Intended Audience :: System Administrators
Classifier: License :: OSI Approved :: MIT License
Classifier: Programming Language :: Python :: 3
Classifier: Operating System :: OS Independent
Requires-Python: >=3.8
License-File: LICENSE.txt
Requires-Dist: cryptography>=44.0.0
Requires-Dist: gssapi>=1.9.0
Requires-Dist: inuxnetutil>=0.1.1
Requires-Dist: ldap3>=2.9.1
